.editorconfig
.gitignore
.readthedocs.yml
LICENSE.txt
MANIFEST.in
README.rst
environment.yml
requirements.txt
setup.cfg
setup.py
umapenhancer_CG_Luoetal.png
versioneer.py
.github/workflows/os_mac.yml
.github/workflows/os_ubuntu.yml
.github/workflows/os_windows.yml
.github/workflows/python-package-conda.yml
.github/workflows/python27-package.yml
.github/workflows/python36-package.yml
.github/workflows/python37-package.yml
.github/workflows/python38-package.yml
.github/workflows/python39-package.yml
docs/Makefile
docs/System_Requirements.rst
docs/basic_usage.rst
docs/conf.py
docs/examples.rst
docs/index.rst
docs/installation.rst
docs/make.bat
docs/references.rst
docs/release_notes.rst
docs/requirements.txt
docs/_static/css/custom.css
docs/_templates/autosummary/base.rst
docs/_templates/autosummary/class.rst
docs/api/index.rst
docs/pictures/Buenrostro_umap.png
docs/pictures/heatmap.png
docs/pictures/pbmc_PCA_coverage.png
docs/pictures/pbmc_diffmap.png
docs/pictures/pbmc_umap.png
docs/pictures/umap.png
docs/pictures/umapSatb2_CLUSTER_NORM.png
docs/pictures/umap_ATACseq_Astrocyte_marker.png
docs/pictures/umap_markers_hodology_ecker.png
docs/pictures/umapenhancer_CG_Luoetal.png
docs/pictures/umapexcitatory_neurons_promoters.png
docs/tutorials/ATAC_bld_ct_mtx_tutorial.html
docs/tutorials/Buenrostro_PBMC_data_processing.html
docs/tutorials/Buenrostro_PBMC_data_processing.ipynb
docs/tutorials/Cusanovich2018_BoneMarrow_data_processing_diffmap.html
docs/tutorials/Tutorial-preprocessing_ATAC_cusanovich.html
docs/tutorials/Tutorial_Hackathon_Buenrostro_2.html
docs/tutorials/Tutorial_building_custom_count_matrices_from_tsv_or_cellranger_outputs.html
docs/tutorials/Tutorial_building_custom_count_matrices_from_tsv_or_cellranger_outputs.ipynb
docs/tutorials/beta_tutorial_10x_pbmc.html
docs/tutorials/bld_count_matrix_methylation_tutorial.html
docs/tutorials/processing_enhancers_mCG.html
docs/tutorials/processing_enhancers_mCG.ipynb
docs/tutorials/tutorial_atac_pbmc_5k_nextgem.ipynb
episcanpy.egg-info/PKG-INFO
episcanpy.egg-info/SOURCES.txt
episcanpy.egg-info/dependency_links.txt
episcanpy.egg-info/not-zip-safe
episcanpy.egg-info/requires.txt
episcanpy.egg-info/top_level.txt
