Metadata-Version: 2.1
Name: episcanpy
Version: 0.4.0
Summary: Epigenomics Single-Cell Analysis in Python.
Home-page: http://github.com/colomemaria/epiScanpy
Author: 
Author-email: 
License: BSD
Platform: UNKNOWN
Classifier: Development Status :: 4 - Beta
Classifier: Environment :: Console
Classifier: Framework :: Jupyter
Classifier: Intended Audience :: Developers
Classifier: Intended Audience :: Science/Research
Classifier: Natural Language :: English
Classifier: Operating System :: MacOS :: MacOS X
Classifier: Operating System :: Microsoft :: Windows
Classifier: Operating System :: POSIX :: Linux
Classifier: Programming Language :: Python :: 3
Classifier: Programming Language :: Python :: 3.5
Classifier: Programming Language :: Python :: 3.6
Classifier: Topic :: Scientific/Engineering :: Bio-Informatics
Classifier: Topic :: Scientific/Engineering :: Visualization
Requires-Python: >=3.5
Provides-Extra: louvain
Provides-Extra: leiden
Provides-Extra: bbknn
Provides-Extra: combat
Provides-Extra: doc
Provides-Extra: test
License-File: LICENSE.txt
